Metadata-Version: 2.1
Name: jac-format
Version: 0.1.4
Summary: JAC (JSON as CSV) Format Conversion
Home-page: https://github.com/UniversalDataTool/jac-format
Author: UniversalDataTool
Author-email: seve@wao.ai
License: MIT
Platform: UNKNOWN
Classifier: Development Status :: 2 - Pre-Alpha
Classifier: Intended Audience :: Science/Research
Classifier: Programming Language :: Python :: 2.7
Classifier: Programming Language :: Python :: 3.6
